MANIFEST.in
setup.cfg
setup.py
torhandlers/__init__.py
torhandlers/base.py
torhandlers/create.py
torhandlers/delete.py
torhandlers/detail.py
torhandlers/edit.py
torhandlers/exceptions.py
torhandlers/form.py
torhandlers/list.py
torhandlers/pagination.py
torhandlers.egg-info/PKG-INFO
torhandlers.egg-info/SOURCES.txt
torhandlers.egg-info/dependency_links.txt
torhandlers.egg-info/not-zip-safe
torhandlers.egg-info/requires.txt
torhandlers.egg-info/top_level.txt
torhandlers/rest/__init__.py
torhandlers/rest/base.py
torhandlers/rest/create.py
torhandlers/rest/delete.py
torhandlers/rest/detail.py
torhandlers/rest/edit.py
torhandlers/rest/form.py
torhandlers/rest/list.py
torhandlers/templating/__init__.py
torhandlers/templating/base.py
torhandlers/templating/exceptions.py
torhandlers/templating/jinja2.py
torhandlers/templating/tornado.py
torhandlers/utils/__init__.py
torhandlers/utils/serialize.py