Metadata-Version: 1.1
Name: torhandlers
Version: 0.1.1
Summary: Library with tornado framework handlers similar to Django's CBV's
Home-page: https://github.com/bosha/torhandlers
Author: Alex Bo
Author-email: bosha@the-bosha.ru
License: MIT
Keywords: tornado,django,generic,json,ajax,rest
Platform: UNKNOWN
Classifier: License :: OSI Approved :: MIT License
Classifier: Programming Language :: Python :: 3.4
